seqits/__init__.py
seqits/__main__.py
seqits/formatseq.py
seqits/randseq.py
seqits/retest.py
seqits/search.py
seqits-0.0.2.dist-info/LICENSE
seqits-0.0.2.dist-info/METADATA
seqits-0.0.2.dist-info/WHEEL
seqits-0.0.2.dist-info/top_level.txt
seqits-0.0.2.dist-info/RECORD
