Metadata-Version: 2.1
Name: seqits
Version: 0.0.2
Summary: Tools for sequences process
Home-page: https://github.com/sfjdx1144/seqits
Author: Fujun Sun
Author-email: sfjdx1144@live.com
License: GPL-3.0 license
Platform: any
Requires-Python: >=3.4.0
License-File: LICENSE
Requires-Dist: argparse
Requires-Dist: colorama
